[
  {
    "thumbnail_photo": "thumb028.jpg",
    "thumbnail_text": "目立たない日々に\nちゃんと意味がある",
    "generated_at": "2026-03-19T22:50:57.992884"
  },
  {
    "thumbnail_photo": "thumb029.jpg",
    "thumbnail_text": "20年前に始めた人との差\nつらい",
    "generated_at": "2026-03-19T22:51:05.188445"
  },
  {
    "thumbnail_photo": "thumb154.jpg",
    "thumbnail_text": "退場しない人だけが勝つ",
    "generated_at": "2026-03-19T22:51:13.075668"
  },
  {
    "thumbnail_photo": "thumb139.jpg",
    "thumbnail_text": "現金のまま\n毎年損してる気がする",
    "generated_at": "2026-03-19T22:51:16.393383"
  },
  {
    "thumbnail_photo": "thumb006.jpg",
    "thumbnail_text": "個別株の勝者は3割以下",
    "generated_at": "2026-03-19T22:51:19.511610"
  },
  {
    "thumbnail_photo": "thumb132.jpg",
    "thumbnail_text": "年利5%の差が\n30年後にこんなに怖い",
    "generated_at": "2026-03-19T23:40:46.116618"
  },
  {
    "thumbnail_photo": "thumb151.jpg",
    "thumbnail_text": "為替が怖い\nでも20年持てば関係ない",
    "generated_at": "2026-03-19T23:40:54.073964"
  },
  {
    "thumbnail_photo": "thumb019.jpg",
    "thumbnail_text": "税金で200万消えてた\n知らなかった人へ",
    "generated_at": "2026-03-19T23:40:57.010963"
  },
  {
    "thumbnail_photo": "thumb004.jpg",
    "thumbnail_text": "続ける意味ある？\n月1万→20年で500万",
    "generated_at": "2026-03-19T23:41:01.718660"
  },
  {
    "thumbnail_photo": "thumb002.jpg",
    "thumbnail_text": "NISA非課税効果、20年で",
    "generated_at": "2026-03-19T23:41:06.233274"
  },
  {
    "thumbnail_photo": "thumb142.jpg",
    "thumbnail_text": "1年続けた人に\n静かに起きていること",
    "generated_at": "2026-03-19T23:41:13.655704"
  },
  {
    "thumbnail_photo": "thumb017.jpg",
    "thumbnail_text": "別の投資に\n乗り換えた人の末路",
    "generated_at": "2026-03-19T23:41:20.282980"
  },
  {
    "thumbnail_photo": "thumb038.jpg",
    "thumbnail_text": "月1万、続けてるのに\n増えない気がする",
    "generated_at": "2026-03-19T23:41:26.295731"
  },
  {
    "thumbnail_photo": "thumb143.jpg",
    "thumbnail_text": "投資、退場\nやめた人、リターン1/3",
    "generated_at": "2026-03-19T23:41:30.220475"
  },
  {
    "thumbnail_photo": "thumb042.jpg",
    "thumbnail_text": "SNSの成功報告\n全部信じてませんか",
    "generated_at": "2026-03-19T23:41:38.133057"
  },
  {
    "thumbnail_photo": "thumb161.jpg",
    "thumbnail_text": "月5万円×30年で",
    "generated_at": "2026-03-19T23:41:44.405281"
  },
  {
    "thumbnail_photo": "thumb059.jpg",
    "thumbnail_text": "積み立て10年目\nやっと意味がわかった話",
    "generated_at": "2026-03-19T23:41:55.255552"
  },
  {
    "thumbnail_photo": "thumb060.jpg",
    "thumbnail_text": "20年続けた人、元本割れゼロ",
    "generated_at": "2026-03-19T23:42:03.808105"
  },
  {
    "thumbnail_photo": "thumb156.jpg",
    "thumbnail_text": "配当5%がうらやましい夜\nインデックス民へ",
    "generated_at": "2026-03-19T23:42:12.043728"
  },
  {
    "thumbnail_photo": "thumb051.jpg",
    "thumbnail_text": "20年続けた人 元本割れゼロ",
    "generated_at": "2026-03-19T23:42:18.116458"
  },
  {
    "thumbnail_photo": "thumb052.jpg",
    "thumbnail_text": "10倍株を\n狙いたくなった人へ",
    "generated_at": "2026-03-19T23:42:23.489189"
  },
  {
    "thumbnail_photo": "thumb164.jpg",
    "thumbnail_text": "高収入じゃなかった\nただ、続けていただけ",
    "generated_at": "2026-03-19T23:42:30.977445"
  },
  {
    "thumbnail_photo": "thumb010.jpg",
    "thumbnail_text": "時間が最大の武器です",
    "generated_at": "2026-03-19T23:42:36.948011"
  },
  {
    "thumbnail_photo": "thumb040.jpg",
    "thumbnail_text": "投資、退場\n3年でやめると翌年を逃す",
    "generated_at": "2026-03-19T23:42:43.697838"
  },
  {
    "thumbnail_photo": "thumb149.jpg",
    "thumbnail_text": "10年、待てない\n10年で勝率95%",
    "generated_at": "2026-03-19T23:42:50.667395"
  },
  {
    "thumbnail_photo": "thumb129.jpg",
    "thumbnail_text": "NISA枠\n使い切れるか不安な人へ",
    "generated_at": "2026-03-19T23:43:00.761061"
  },
  {
    "thumbnail_photo": "thumb008.jpg",
    "thumbnail_text": "つらい\n月1万、20年で500万",
    "generated_at": "2026-03-19T23:43:05.219936"
  },
  {
    "thumbnail_photo": "thumb134.jpg",
    "thumbnail_text": "長期投資しかないですね",
    "generated_at": "2026-03-19T23:43:12.606915"
  },
  {
    "thumbnail_photo": "thumb012.jpg",
    "thumbnail_text": "退屈な投資を\nしている人へ",
    "generated_at": "2026-03-19T23:43:19.482033"
  },
  {
    "thumbnail_photo": "thumb162.jpg",
    "thumbnail_text": "積み立て3年目\nやめた翌年が一番伸びる",
    "generated_at": "2026-03-19T23:43:23.395807"
  },
  {
    "thumbnail_photo": "thumb055.jpg",
    "thumbnail_text": "向いてない\nやめた人、1/3",
    "generated_at": "2026-03-19T23:43:28.461296"
  },
  {
    "thumbnail_photo": "thumb011.jpg",
    "thumbnail_text": "暴落\n恐慌から25年で10倍",
    "generated_at": "2026-03-19T23:43:37.708728"
  },
  {
    "thumbnail_photo": "thumb049.jpg",
    "thumbnail_text": "複利に気づくのは10年後\nそれでいい",
    "generated_at": "2026-03-19T23:43:45.010111"
  },
  {
    "thumbnail_photo": "thumb020.jpg",
    "thumbnail_text": "暴落後1年のリターン、平均+",
    "generated_at": "2026-03-19T23:43:52.043892"
  },
  {
    "thumbnail_photo": "thumb046.jpg",
    "thumbnail_text": "増えない\n3年でやめた人は翌年逃す",
    "generated_at": "2026-03-19T23:43:57.239511"
  },
  {
    "thumbnail_photo": "thumb152.jpg",
    "thumbnail_text": "月5000円で",
    "generated_at": "2026-03-19T23:44:04.662661"
  },
  {
    "thumbnail_photo": "thumb147.jpg",
    "thumbnail_text": "投資で一番の味方\n気づいてますか",
    "generated_at": "2026-03-19T23:44:09.628447"
  },
  {
    "thumbnail_photo": "thumb037.jpg",
    "thumbnail_text": "コロナ後、1年半で最高値更新",
    "generated_at": "2026-03-19T23:44:14.924311"
  },
  {
    "thumbnail_photo": "thumb009.jpg",
    "thumbnail_text": "増えない\n積み立て10年目から加速",
    "generated_at": "2026-03-19T23:44:22.784472"
  },
  {
    "thumbnail_photo": "thumb138.jpg",
    "thumbnail_text": "30年後に\n追いつける計算がある",
    "generated_at": "2026-03-19T23:44:30.964783"
  },
  {
    "thumbnail_photo": "thumb132.jpg",
    "thumbnail_text": "焦り\n勝者は生存者バイアス",
    "generated_at": "2026-03-19T23:44:38.031909"
  },
  {
    "thumbnail_photo": "thumb130.jpg",
    "thumbnail_text": "平均リターン年7%、ただし毎",
    "generated_at": "2026-03-19T23:44:44.801774"
  },
  {
    "thumbnail_photo": "thumb004.jpg",
    "thumbnail_text": "2年やってプラマイゼロ\nそれでも続ける理由",
    "generated_at": "2026-03-19T23:44:49.207432"
  },
  {
    "thumbnail_photo": "thumb141.jpg",
    "thumbnail_text": "インフレに勝てるのは株だけ",
    "generated_at": "2026-03-19T23:44:58.383185"
  },
  {
    "thumbnail_photo": "thumb033.jpg",
    "thumbnail_text": "焦り\nレバレッジ9割が退場",
    "generated_at": "2026-03-19T23:45:05.757017"
  },
  {
    "thumbnail_photo": "thumb014.jpg",
    "thumbnail_text": "3年続けたあなたは\nもう上位10%にいる",
    "generated_at": "2026-03-19T23:45:11.873075"
  },
  {
    "thumbnail_photo": "thumb148.jpg",
    "thumbnail_text": "保有3年でやめた人、翌年逃す",
    "generated_at": "2026-03-19T23:45:18.164970"
  },
  {
    "thumbnail_photo": "thumb056.jpg",
    "thumbnail_text": "複利の力\n資産99%は50歳以降",
    "generated_at": "2026-03-19T23:45:22.343222"
  },
  {
    "thumbnail_photo": "thumb062.jpg",
    "thumbnail_text": "増えてない、それで",
    "generated_at": "2026-03-19T23:45:31.824428"
  },
  {
    "thumbnail_photo": "thumb139.jpg",
    "thumbnail_text": "口座を見るたびに\n不安になってる",
    "generated_at": "2026-03-19T23:45:35.193537"
  },
  {
    "thumbnail_photo": "thumb054.jpg",
    "thumbnail_text": "焦り\n10倍株の確率1%未満",
    "generated_at": "2026-03-19T23:45:41.010213"
  },
  {
    "thumbnail_photo": "thumb032.jpg",
    "thumbnail_text": "iDeCoを\n待てなかった人の後悔",
    "generated_at": "2026-03-19T23:45:45.962137"
  },
  {
    "thumbnail_photo": "thumb048.jpg",
    "thumbnail_text": "積み立て、忘れてた\n最悪タイミングでも利益",
    "generated_at": "2026-03-19T23:45:51.705698"
  },
  {
    "thumbnail_photo": "thumb058.jpg",
    "thumbnail_text": "10年遅れた後悔\nでも、今日が一番早い",
    "generated_at": "2026-03-19T23:45:55.800745"
  },
  {
    "thumbnail_photo": "thumb039.jpg",
    "thumbnail_text": "下がった時に買えない\nあの躊躇、わかります",
    "generated_at": "2026-03-19T23:46:01.122827"
  },
  {
    "thumbnail_photo": "thumb137.jpg",
    "thumbnail_text": "世界経済、100年で25倍",
    "generated_at": "2026-03-19T23:46:06.880199"
  },
  {
    "thumbnail_photo": "thumb159.jpg",
    "thumbnail_text": "年初一括か積み立てか\nまた同じ議論してる",
    "generated_at": "2026-03-19T23:46:14.318446"
  },
  {
    "thumbnail_photo": "thumb034.jpg",
    "thumbnail_text": "やめるとリターン3分の1",
    "generated_at": "2026-03-19T23:46:21.467766"
  },
  {
    "thumbnail_photo": "thumb047.jpg",
    "thumbnail_text": "積み立て、変えなかった\nそれだけで十分です",
    "generated_at": "2026-03-19T23:46:26.662648"
  },
  {
    "thumbnail_photo": "thumb149.jpg",
    "thumbnail_text": "勉強するほどブレる人へ",
    "generated_at": "2026-03-19T23:46:33.705927"
  },
  {
    "thumbnail_photo": "thumb052.jpg",
    "thumbnail_text": "積み立てが\n無駄かもと思ったあなたへ",
    "generated_at": "2026-03-19T23:46:39.259341"
  },
  {
    "thumbnail_photo": "thumb041.jpg",
    "thumbnail_text": "月1万でも20年で500万",
    "generated_at": "2026-03-19T23:46:43.243005"
  },
  {
    "thumbnail_photo": "thumb022.jpg",
    "thumbnail_text": "目立たない日々に\nちゃんと意味がある",
    "generated_at": "2026-03-19T23:46:51.219711"
  },
  {
    "thumbnail_photo": "thumb011.jpg",
    "thumbnail_text": "20年前に始めた人との差\nつらい",
    "generated_at": "2026-03-19T23:47:00.954284"
  },
  {
    "thumbnail_photo": "thumb156.jpg",
    "thumbnail_text": "退場しない人だけが勝つ",
    "generated_at": "2026-03-19T23:47:09.870004"
  },
  {
    "thumbnail_photo": "thumb035.jpg",
    "thumbnail_text": "現金のまま\n毎年損してる気がする",
    "generated_at": "2026-03-19T23:47:17.440945"
  },
  {
    "thumbnail_photo": "thumb131.jpg",
    "thumbnail_text": "個別株の勝者は3割以下",
    "generated_at": "2026-03-19T23:47:22.721596"
  },
  {
    "thumbnail_photo": "thumb069.jpg",
    "thumbnail_text": "20年、元本割れゼロ",
    "generated_at": "2026-03-22T08:32:28.232644"
  },
  {
    "thumbnail_photo": "thumb092.jpg",
    "thumbnail_text": "20年で約200万非課税",
    "generated_at": "2026-03-22T08:33:36.924241"
  },
  {
    "thumbnail_photo": "thumb001.jpg",
    "thumbnail_text": "月1万→20年で500万",
    "generated_at": "2026-03-22T08:34:50.387085"
  },
  {
    "thumbnail_photo": "thumb017.jpg",
    "thumbnail_text": "年7%で10年、元本2倍",
    "generated_at": "2026-03-22T08:36:20.049699"
  },
  {
    "thumbnail_photo": "thumb160.jpg",
    "thumbnail_text": "勝った人しか叫ばない",
    "generated_at": "2026-03-22T08:37:27.120937"
  },
  {
    "thumbnail_photo": "thumb118.jpg",
    "thumbnail_text": "20年続けた人、元本割れゼロ",
    "generated_at": "2026-03-22T08:38:49.241919"
  },
  {
    "thumbnail_photo": "thumb098.jpg",
    "thumbnail_text": "淡々と続けた人が最後に笑う",
    "generated_at": "2026-03-22T08:40:02.841488"
  },
  {
    "thumbnail_photo": "thumb075.jpg",
    "thumbnail_text": "15年持った人、全員プラス",
    "generated_at": "2026-03-22T08:41:25.177395"
  },
  {
    "thumbnail_photo": "thumb050.jpg",
    "thumbnail_text": "テンバガー狙って疲れてません",
    "generated_at": "2026-03-22T08:42:45.610132"
  },
  {
    "thumbnail_photo": "thumb105.jpg",
    "thumbnail_text": "年7%で10年2倍",
    "generated_at": "2026-03-22T08:43:53.406999"
  },
  {
    "thumbnail_photo": "thumb019.jpg",
    "thumbnail_text": "800万円の差。信託報酬0.",
    "generated_at": "2026-03-22T08:45:12.606713"
  },
  {
    "thumbnail_photo": "thumb053.jpg",
    "thumbnail_text": "続いているだけで十分",
    "generated_at": "2026-03-22T08:46:13.864221"
  },
  {
    "thumbnail_photo": "thumb081.jpg",
    "thumbnail_text": "投資に疲れた",
    "generated_at": "2026-03-26T17:07:09.291088"
  },
  {
    "thumbnail_photo": "thumb018.jpg",
    "thumbnail_text": "暴落\n暴落後1年、平均＋25%",
    "generated_at": "2026-03-28T20:47:14.164630"
  },
  {
    "thumbnail_photo": "thumb027.jpg",
    "thumbnail_text": "積み立てが\n怖くなった人へ",
    "generated_at": "2026-03-31T13:30:59.021412"
  },
  {
    "thumbnail_photo": "thumb130.jpg",
    "thumbnail_text": "利確しすぎると差がつく",
    "generated_at": "2026-03-31T13:33:34.957933"
  },
  {
    "thumbnail_photo": "thumb112.jpg",
    "thumbnail_text": "暴落で売った人が\n1年後に後悔した数字",
    "generated_at": "2026-04-02T11:19:34.901946"
  },
  {
    "thumbnail_photo": "thumb114.jpg",
    "thumbnail_text": "恐怖指数が高い時に買った人が",
    "generated_at": "2026-04-02T11:21:37.722029"
  },
  {
    "thumbnail_photo": "thumb078.jpg",
    "thumbnail_text": "積み立て1年休んだ人が\n失った150万円",
    "generated_at": "2026-04-02T11:25:11.531051"
  },
  {
    "thumbnail_photo": "thumb146.jpg",
    "thumbnail_text": "迷う時間も投資",
    "generated_at": "2026-04-02T11:27:17.398854"
  },
  {
    "thumbnail_photo": "thumb163.jpg",
    "thumbnail_text": "売った途端に\n上がった人へ",
    "generated_at": "2026-04-02T11:29:32.969502"
  },
  {
    "thumbnail_photo": "thumb104.jpg",
    "thumbnail_text": "タイミングを当て続けるのは難",
    "generated_at": "2026-04-02T11:31:11.248780"
  },
  {
    "thumbnail_photo": "thumb008.jpg",
    "thumbnail_text": "乗り換えた人の半数が元に戻る",
    "generated_at": "2026-04-02T11:33:11.994087"
  },
  {
    "thumbnail_photo": "thumb141.jpg",
    "thumbnail_text": "3年で別の投資に\n乗り換えた人へ",
    "generated_at": "2026-04-02T11:35:04.503028"
  },
  {
    "thumbnail_photo": "thumb049.jpg",
    "thumbnail_text": "積み立てを\n止めた人へ",
    "generated_at": "2026-04-02T11:38:14.335107"
  },
  {
    "thumbnail_photo": "thumb002.jpg",
    "thumbnail_text": "手数料1%が\n怖い理由",
    "generated_at": "2026-04-02T11:40:11.735474"
  },
  {
    "thumbnail_photo": "thumb099.jpg",
    "thumbnail_text": "売った人の9割が回復を逃した",
    "generated_at": "2026-04-02T11:42:43.719889"
  },
  {
    "thumbnail_photo": "thumb012.jpg",
    "thumbnail_text": "暴落の後が分岐点",
    "generated_at": "2026-04-02T11:44:43.645725"
  },
  {
    "thumbnail_photo": "thumb003.jpg",
    "thumbnail_text": "ITバブル崩壊\n13年待った人へ",
    "generated_at": "2026-04-02T11:46:56.420631"
  },
  {
    "thumbnail_photo": "thumb100.jpg",
    "thumbnail_text": "やめた人が逃した\n過去50年の上昇",
    "generated_at": "2026-04-02T11:48:55.318904"
  },
  {
    "thumbnail_photo": "thumb054.jpg",
    "thumbnail_text": "30歳で\n投資を始めるのが怖い人へ",
    "generated_at": "2026-04-02T12:05:09.596088"
  },
  {
    "thumbnail_photo": "thumb101.jpg",
    "thumbnail_text": "レバレッジの9割が5年で退場",
    "generated_at": "2026-04-02T12:08:08.366839"
  },
  {
    "thumbnail_photo": "thumb122.jpg",
    "thumbnail_text": "高配当ETFが\n羨ましくなった人へ",
    "generated_at": "2026-04-02T12:12:46.717702"
  }
]